hyperagent.cpython-312-darwin.so
hyperagent.pyi
hyperagent-0.0.3.dist-info/RECORD
hyperagent-0.0.3.dist-info/WHEEL
hyperagent-0.0.3.dist-info/entry_points.txt
hyperagent-0.0.3.dist-info/top_level.txt
hyperagent-0.0.3.dist-info/METADATA
hyperagent-0.0.3.dist-info/licenses/LICENSE
