Metadata-Version: 2.4
Name: hyperagent
Version: 0.0.3
Summary: multimoda Agent framework
Author-email: Yaqiang Sun <sunyaking@163.com>
License: GPL-3.0
Requires-Python: <3.14,>=3.12
License-File: LICENSE
Requires-Dist: aiohttp>=3.13.2
Requires-Dist: fastmcp>=2.14.2
Requires-Dist: ms-agent>=1.5.2
Requires-Dist: ms-enclave[docker]>=0.0.4
Requires-Dist: omegaconf>=2.3.0
Requires-Dist: pandas>=2.3.3
Provides-Extra: research
Requires-Dist: arxiv; extra == "research"
Requires-Dist: docling<=2.38.1; extra == "research"
Requires-Dist: docling-core<=2.38.2; extra == "research"
Requires-Dist: exa-py; extra == "research"
Requires-Dist: google-search-results; extra == "research"
Requires-Dist: json5; extra == "research"
Requires-Dist: markdown; extra == "research"
Requires-Dist: modelscope; extra == "research"
Requires-Dist: openai; extra == "research"
Requires-Dist: Pillow; extra == "research"
Requires-Dist: python-dotenv; extra == "research"
Requires-Dist: ray[default]>=2.53.0; extra == "research"
Requires-Dist: requests; extra == "research"
Dynamic: license-file
